artimers/AdvancedTimer.py
artimers/GlobalTimer.py
artimers/SimpleTimer.py
artimers/__init__.py
artimers-1.0.1.dist-info/licenses/LICENSE
artimers-1.0.1.dist-info/METADATA
artimers-1.0.1.dist-info/WHEEL
artimers-1.0.1.dist-info/top_level.txt
artimers-1.0.1.dist-info/RECORD
