Metadata-Version: 2.4
Name: artimers
Version: 1.0.1
Summary: A utility package for timing and managing timers.
Author-email: Alexander Rießbeck <alexanderriessbeck@gmail.com>
License: MIT
Project-URL: Homepage, https://gitlab.com/alexander-riessbeck/artimer
Project-URL: Source, https://gitlab.com/alexander-riessbeck/artimer
Project-URL: Issues, https://gitlab.com/alexander-riessbeck/artimer/issues
Keywords: Timer,Timing,class,contextmanager,decorator
Requires-Python: >=3.8
License-File: LICENSE
Dynamic: license-file
